[
    {
        "type": "radiobutton",
        "name": "q1",
        "label": "Le label de la question 1.",
        "choices": ["Answer 1", "Answer 2", "Answer 3"],
        "required": true,
        "defaultValue": "Answer 2"
    },
    {
        "type": "checkbox",
        "name": "q2",
        "label": "Le label de la question 2.",
        "choices": ["Answer 1", "Answer 2", "Answer 3"],
        "required": false,
        "defaultValue": ""
    },
    {
        "type": "textfield",
        "name": "q3",
        "label": "Le label de la question 3.",
        "required": true,
        "defaultValue": "Default Text"
    }
]
